traccia/__init__.py
traccia/auto.py
traccia/auto_instrumentation.py
traccia/cli.py
traccia/config.py
traccia/errors.py
traccia/pricing_config.py
traccia/runtime_config.py
traccia/context/__init__.py
traccia/context/context.py
traccia/context/propagators.py
traccia/exporter/__init__.py
traccia/exporter/console_exporter.py
traccia/exporter/file_exporter.py
traccia/exporter/http_exporter.py
traccia/exporter/otlp_exporter.py
traccia/instrumentation/__init__.py
traccia/instrumentation/anthropic.py
traccia/instrumentation/decorator.py
traccia/instrumentation/fastapi.py
traccia/instrumentation/http_client.py
traccia/instrumentation/http_server.py
traccia/instrumentation/openai.py
traccia/instrumentation/requests.py
traccia/integrations/__init__.py
traccia/integrations/langchain/__init__.py
traccia/integrations/langchain/callback.py
traccia/integrations/langchain/utils.py
traccia/processors/__init__.py
traccia/processors/agent_enricher.py
traccia/processors/batch_processor.py
traccia/processors/cost_engine.py
traccia/processors/cost_processor.py
traccia/processors/drop_policy.py
traccia/processors/logging_processor.py
traccia/processors/rate_limiter.py
traccia/processors/sampler.py
traccia/processors/token_counter.py
traccia/tracer/__init__.py
traccia/tracer/otel_adapter.py
traccia/tracer/otel_utils.py
traccia/tracer/provider.py
traccia/tracer/span.py
traccia/tracer/span_context.py
traccia/tracer/tracer.py
traccia/utils/__init__.py
traccia/utils/helpers.py
traccia-0.1.5.dist-info/licenses/LICENSE
traccia-0.1.5.dist-info/METADATA
traccia-0.1.5.dist-info/WHEEL
traccia-0.1.5.dist-info/entry_points.txt
traccia-0.1.5.dist-info/top_level.txt
traccia-0.1.5.dist-info/RECORD
