Metadata-Version: 2.4
Name: traccia
Version: 0.1.5
Summary: Production-ready distributed tracing SDK for AI agents and LLM applications
License: Apache-2.0
Project-URL: Homepage, https://github.com/traccia-ai/traccia
Project-URL: Documentation, https://github.com/traccia-ai/traccia#readme
Project-URL: Repository, https://github.com/traccia-ai/traccia
Project-URL: Issues, https://github.com/traccia-ai/traccia/issues
Project-URL: Bug Tracker, https://github.com/traccia-ai/traccia/issues
Keywords: tracing,observability,opentelemetry,ai-agents,llm,distributed-tracing,monitoring,telemetry
Classifier: Development Status :: 4 - Beta
Classifier: Intended Audience :: Developers
Classifier: License :: OSI Approved :: Apache Software License
Classifier: Operating System :: OS Independent
Classifier: Programming Language :: Python :: 3
Classifier: Programming Language :: Python :: 3.9
Classifier: Programming Language :: Python :: 3.10
Classifier: Programming Language :: Python :: 3.11
Classifier: Programming Language :: Python :: 3.12
Classifier: Topic :: Software Development :: Libraries :: Python Modules
Classifier: Topic :: System :: Monitoring
Classifier: Topic :: Software Development :: Testing
Requires-Python: >=3.9
License-File: LICENSE
Requires-Dist: tiktoken>=0.7.0
Requires-Dist: opentelemetry-api>=1.20.0
Requires-Dist: opentelemetry-sdk>=1.20.0
Requires-Dist: opentelemetry-exporter-otlp-proto-http>=1.20.0
Requires-Dist: opentelemetry-semantic-conventions>=0.40b0
Requires-Dist: tomli>=2.0.0; python_version < "3.11"
Requires-Dist: toml>=0.10.0
Requires-Dist: pydantic>=2.0.0
Provides-Extra: langchain
Requires-Dist: langchain-core>=0.1.0; extra == "langchain"
Dynamic: license-file
